ortfodb/__init__.py
ortfodb/configuration.py
ortfodb/database.py
ortfodb/exporter.py
ortfodb/tags.py
ortfodb/technologies.py
ortfodb-1.6.1.dist-info/METADATA
ortfodb-1.6.1.dist-info/WHEEL
ortfodb-1.6.1.dist-info/RECORD
