Metadata-Version: 2.1
Name: ortfodb
Version: 1.6.1
Summary: ortfodb client library
License: MIT
Author: Ewen Le Bihan
Author-email: hey@ewen.works
Requires-Python: >=3.11,<4.0
Classifier: License :: OSI Approved :: MIT License
Classifier: Programming Language :: Python :: 3
Classifier: Programming Language :: Python :: 3.11
Classifier: Programming Language :: Python :: 3.12
